{"cameraMode":{"drawMode":0,"name":"Shaded","section":"Shading Mode"},"sceneLighting":false,"audioPlay":false,"sceneViewState":{"m_AlwaysRefresh":false,"showFog":true,"showSkybox":false,"showFlares":true,"showImageEffects":true,"showParticleSystems":true,"showVisualEffectGraphs":true,"m_FxEnabled":true},"in2DMode":false,"pivot":{"x":7.216000080108643,"y":2.8910000324249269,"z":0.026000022888183595},"rotation":{"x":0.20565776526927949,"y":-0.6599740982055664,"z":0.19507578015327454,"w":0.6957722902297974},"size":8.444656372070313,"orthographic":false}